LICENSE
MANIFEST.in
README.md
setup.py
bddl/__init__.py
bddl/activity.py
bddl/activity_manifest.txt
bddl/activity_to_preselected_scenes.json
bddl/backend_abc.py
bddl/bddl_verification.py
bddl/condition_evaluation.py
bddl/config.py
bddl/logic_base.py
bddl/object_taxonomy.py
bddl/parsing.py
bddl/trivial_backend.py
bddl/utils.py
bddl.egg-info/PKG-INFO
bddl.egg-info/SOURCES.txt
bddl.egg-info/dependency_links.txt
bddl.egg-info/not-zip-safe
bddl.egg-info/requires.txt
bddl.egg-info/top_level.txt
bddl/activity_definitions/domain_igibson.bddl
bddl/activity_definitions/domain_omnigibson.bddl
bddl/activity_definitions/adding_chemicals_to_hot_tub/problem0.bddl
bddl/activity_definitions/adding_chemicals_to_lawn/problem0.bddl
bddl/activity_definitions/adding_chemicals_to_pool/problem0.bddl
bddl/activity_definitions/adding_fabric_softener/problem0.bddl
bddl/activity_definitions/applying_pesticides/problem0.bddl
bddl/activity_definitions/assembling_furniture/problem0.bddl
bddl/activity_definitions/assembling_gift_baskets/problem0.bddl
bddl/activity_definitions/attach_a_camera_to_a_tripod/problem0.bddl
bddl/activity_definitions/bag_groceries/problem0.bddl
bddl/activity_definitions/baking_cookies_for_the_PTA_bake_sale/problem0.bddl
bddl/activity_definitions/baking_sugar_cookies/problem0.bddl
bddl/activity_definitions/boil_water/problem0.bddl
bddl/activity_definitions/boil_water_in_the_microwave/problem0.bddl
bddl/activity_definitions/bottling_wine/problem0.bddl
bddl/activity_definitions/boxing_books_up_for_storage/problem0.bddl
bddl/activity_definitions/boxing_food_after_dinner/problem0.bddl
bddl/activity_definitions/brewing_coffee/problem0.bddl
bddl/activity_definitions/bringing_glass_to_recycling/problem0.bddl
bddl/activity_definitions/bringing_in_kindling/problem0.bddl
bddl/activity_definitions/bringing_in_mail/problem0.bddl
bddl/activity_definitions/bringing_in_wood/problem0.bddl
bddl/activity_definitions/bringing_laundry/problem0.bddl
bddl/activity_definitions/bringing_newspaper_in/problem0.bddl
bddl/activity_definitions/bringing_paper_to_recycling/problem0.bddl
bddl/activity_definitions/bringing_water/problem0.bddl
