Metadata-Version: 2.4
Name: bddl
Version: 3.6.0
Home-page: https://github.com/StanfordVL/bddl
Author: Stanford University
License-File: LICENSE
Requires-Dist: pytest
Requires-Dist: numpy
Requires-Dist: networkx
Requires-Dist: jupytext
Requires-Dist: future
Requires-Dist: nltk~=3.7
Dynamic: author
Dynamic: description
Dynamic: description-content-type
Dynamic: home-page
Dynamic: license-file
Dynamic: requires-dist
